fastapi_and_caching/__init__.py
fastapi_and_caching/backends/__init__.py
fastapi_and_caching/backends/base.py
fastapi_and_caching/backends/redis.py
fastapi_and_caching-0.0.11.dist-info/LICENSE
fastapi_and_caching-0.0.11.dist-info/METADATA
fastapi_and_caching-0.0.11.dist-info/WHEEL
fastapi_and_caching-0.0.11.dist-info/RECORD
