Metadata-Version: 2.1
Name: fastapi-and-caching
Version: 0.0.11
Summary: Easily use caching in FastAPI!
Home-page: https://github.com/heysaeid/fastapi-and-caching
License: MIT
Keywords: fastapi,fastapi caching,fastapi and caching
Author: Saeid Noormohammadi
Author-email: heysaeid92@gmail.com
Requires-Python: >=3.7,<4.0
Classifier: License :: OSI Approved :: MIT License
Classifier: Programming Language :: Python :: 3
Classifier: Programming Language :: Python :: 3.7
Classifier: Programming Language :: Python :: 3.8
Classifier: Programming Language :: Python :: 3.9
Classifier: Programming Language :: Python :: 3.10
Classifier: Programming Language :: Python :: 3.11
Classifier: Programming Language :: Python :: 3.12
Requires-Dist: fastapi
Requires-Dist: redis (>=4.5.0)
Project-URL: Documentation, https://github.com/heysaeid/fastapi-and-caching
Project-URL: Repository, https://github.com/heysaeid/fastapi-and-caching
